decpy/__init__.py
decpy/decpy.py
decpy-2.0.0.dist-info/METADATA
decpy-2.0.0.dist-info/WHEEL
decpy-2.0.0.dist-info/top_level.txt
decpy-2.0.0.dist-info/RECORD
