Metadata-Version: 2.4
Name: decpy
Version: 2.0.0
Summary: Declarative Programming Tools
Home-page: https://github.com/pauldobriak/DecPy
Author: Paul Dobryak
Author-email: goodsoul@mail.ru
Project-URL: GitHub, https://github.com/pauldobriak/DecPy
Dynamic: author
Dynamic: author-email
Dynamic: description
Dynamic: description-content-type
Dynamic: home-page
Dynamic: project-url
Dynamic: summary
